x_axis/__init__.py
x_axis/overlap.py
x_axis_lib-0.0.2.dist-info/METADATA
x_axis_lib-0.0.2.dist-info/WHEEL
x_axis_lib-0.0.2.dist-info/top_level.txt
x_axis_lib-0.0.2.dist-info/RECORD
