Metadata-Version: 2.1
Name: x-axis-lib
Version: 0.0.2
Summary: module for testing weheather 2 x axis are overlapping
Home-page: https://github.com/qalfaki/py-lib/tree/master/x_axis_lib
Author: qalfaki
Author-email: qusai.alfaki@gmail.com
License: UNKNOWN
Platform: UNKNOWN
Classifier: Programming Language :: Python :: 3
Classifier: License :: OSI Approved :: MIT License
Classifier: Operating System :: OS Independent
Requires-Python: >=3.6
